[
{
	"input": "Sell it and use the money to buy gold"
},
{
	"input": "Homeless people house"
},
{
	"input": "Pavilion building"
},
{
	"input": "Bridge"
},
{
	"input": "Furniture, cupboard, bed, etc"
},
{
	"input": "Toys"
},
{
	"input": "Arts, sculptures"
},
{
	"input": "A burner phone"
},
{
	"input": "Single-use camera"
},
{
	"input": "Serving tray"
},
{
	"input": "Placemats, coasters, table mats"
},
{
	"input": "Picnic mat"
},
{
	"input": "Book cover"
},
{
	"input": "Partition"
},
{
	"input": "Garden bench"
},
{
	"input": "Biodegradable plant pots"
},
{
	"input": "Urn, ash floating Ceremony"
},
{
	"input": "Boat"
},
{
	"input": "Roll it into a cylinder to make Naga fireballs"
},
{
	"input": "Shockproof in logistics"
},
{
	"input": "Teaset"
},
{
	"input": "Water filter"
},
{
	"input": "Traffic sign"
},
{
	"input": "Traffic cone"
},
{
	"input": "Beer keg, wine keg"
},
{
	"input": "Cheese fermentation tank"
},
{
	"input": "Campaign Signs for election"
},
{
	"input": "Glider"
},
{
	"input": "Food container"
},
{
	"input": "Vegetable plot"
},
{
	"input": "Coffin"
},
{
	"input": "Talipot fan"
},
{
	"input": "Emergency stretcher"
}
]